{"chunk_definitions":[{"row":17,"row_count":1,"visible":true,"expansion_state":0,"options":{"engine":"r","label":"unnamed-chunk-89","dev":"png"},"document_id":"64053CAA","chunk_id":"cj1t6sv6867jz","chunk_label":"unnamed-chunk-1"},{"row":24,"row_count":1,"visible":true,"expansion_state":0,"options":{"engine":"r","label":"unnamed-chunk-82","dev":"png"},"document_id":"64053CAA","chunk_id":"ci6jgzdsbmril","chunk_label":"unnamed-chunk-2"},{"row":37,"row_count":1,"visible":true,"expansion_state":0,"options":{"engine":"r","label":"unnamed-chunk-83","dev":"png"},"document_id":"64053CAA","chunk_id":"cfcpoenc1k5ps","chunk_label":"unnamed-chunk-3"},{"row":50,"row_count":1,"visible":true,"expansion_state":0,"options":{"engine":"r","label":"unnamed-chunk-84","dev":"png"},"document_id":"64053CAA","chunk_id":"cgdx0skdph1sv","chunk_label":"unnamed-chunk-4"},{"row":60,"row_count":1,"visible":true,"expansion_state":0,"options":{"engine":"r","label":"unnamed-chunk-85","dev":"png"},"document_id":"64053CAA","chunk_id":"con421yirl0n5","chunk_label":"unnamed-chunk-5"},{"row":77,"row_count":1,"visible":true,"expansion_state":0,"options":{"engine":"r","label":"unnamed-chunk-86","dev":"png"},"document_id":"64053CAA","chunk_id":"c6isn04kkq010","chunk_label":"unnamed-chunk-6"}],"doc_write_time":1720040938,"chunk_rendered_width":700}